[{"id":-10000,"lat":0,"lng":0,"name":"热门商区","parentId":0,"regionType":0},{"id":0,"lat":0,"lng":0,"name":"全部商区","parentId":-10000,"regionType":0},{"id":72942,"lat":0,"lng":0,"name":"清红路","parentId":-10000,"regionType":0},{"id":72944,"lat":0,"lng":0,"name":"龙祥路","parentId":-10000,"regionType":0},{"id":72947,"lat":0,"lng":0,"name":"世纪商城","parentId":-10000,"regionType":0},{"id":58953,"lat":0,"lng":0,"name":"祥城镇","parentId":0,"regionType":0},{"id":58953,"lat":0,"lng":0,"name":"全部祥城镇","parentId":58953,"regionType":0},{"id":58955,"lat":0,"lng":0,"name":"云南驿镇","parentId":0,"regionType":0},{"id":58955,"lat":0,"lng":0,"name":"全部云南驿镇","parentId":58955,"regionType":0},{"id":58956,"lat":0,"lng":0,"name":"下庄镇","parentId":0,"regionType":0},{"id":58956,"lat":0,"lng":0,"name":"全部下庄镇","parentId":58956,"regionType":0},{"id":5294,"lat":0,"lng":0,"name":"祥云县其他","parentId":0,"regionType":0},{"id":5294,"lat":0,"lng":0,"name":"全部祥云县其他","parentId":5294,"regionType":0},{"id":72942,"lat":0,"lng":0,"name":"清红路","parentId":5294,"regionType":0},{"id":72944,"lat":0,"lng":0,"name":"龙祥路","parentId":5294,"regionType":0},{"id":72947,"lat":0,"lng":0,"name":"世纪商城","parentId":5294,"regionType":0},{"id":58957,"lat":0,"lng":0,"name":"普棚镇","parentId":0,"regionType":0},{"id":58957,"lat":0,"lng":0,"name":"全部普棚镇","parentId":58957,"regionType":0},{"id":58960,"lat":0,"lng":0,"name":"米甸镇","parentId":0,"regionType":0},{"id":58960,"lat":0,"lng":0,"name":"全部米甸镇","parentId":58960,"regionType":0},{"id":58959,"lat":0,"lng":0,"name":"禾甸镇","parentId":0,"regionType":0},{"id":58959,"lat":0,"lng":0,"name":"全部禾甸镇","parentId":58959,"regionType":0},{"id":58958,"lat":0,"lng":0,"name":"刘厂镇","parentId":0,"regionType":0},{"id":58958,"lat":0,"lng":0,"name":"全部刘厂镇","parentId":58958,"regionType":0},{"id":58954,"lat":0,"lng":0,"name":"沙龙镇","parentId":0,"regionType":0},{"id":58954,"lat":0,"lng":0,"name":"全部沙龙镇","parentId":58954,"regionType":0},{"id":58961,"lat":0,"lng":0,"name":"鹿鸣乡","parentId":0,"regionType":0},{"id":58961,"lat":0,"lng":0,"name":"全部鹿鸣乡","parentId":58961,"regionType":0},{"id":58962,"lat":0,"lng":0,"name":"东山彝族乡","parentId":0,"regionType":0},{"id":58962,"lat":0,"lng":0,"name":"全部东山彝族乡","parentId":58962,"regionType":0}]