[{"id":-10000,"lat":0,"lng":0,"name":"热门商区","parentId":0,"regionType":0},{"id":0,"lat":0,"lng":0,"name":"全部商区","parentId":-10000,"regionType":0},{"id":29645,"lat":0,"lng":0,"name":"平朔路","parentId":-10000,"regionType":0},{"id":29646,"lat":0,"lng":0,"name":"金龙商业街","parentId":-10000,"regionType":0},{"id":29647,"lat":0,"lng":0,"name":"宝源商务","parentId":-10000,"regionType":0},{"id":41854,"lat":0,"lng":0,"name":"云中镇","parentId":-10000,"regionType":0},{"id":77229,"lat":0,"lng":0,"name":"中国邮政","parentId":-10000,"regionType":0},{"id":41822,"lat":0,"lng":0,"name":"岱岳镇","parentId":-10000,"regionType":0},{"id":77232,"lat":0,"lng":0,"name":"建设银行","parentId":-10000,"regionType":0},{"id":77261,"lat":0,"lng":0,"name":"友谊街","parentId":-10000,"regionType":0},{"id":41832,"lat":0,"lng":0,"name":"金城镇","parentId":-10000,"regionType":0},{"id":77206,"lat":0,"lng":0,"name":"七里河","parentId":-10000,"regionType":0},{"id":77251,"lat":0,"lng":0,"name":"民福街","parentId":-10000,"regionType":0},{"id":41844,"lat":0,"lng":0,"name":"新城镇","parentId":-10000,"regionType":0},{"id":41839,"lat":0,"lng":0,"name":"杏寨乡","parentId":-10000,"regionType":0},{"id":41859,"lat":0,"lng":0,"name":"新家园乡","parentId":-10000,"regionType":0},{"id":41860,"lat":0,"lng":0,"name":"亲和乡","parentId":-10000,"regionType":0},{"id":41831,"lat":0,"lng":0,"name":"马营庄乡","parentId":-10000,"regionType":0},{"id":41836,"lat":0,"lng":0,"name":"义井乡","parentId":-10000,"regionType":0},{"id":41842,"lat":0,"lng":0,"name":"大临河乡","parentId":-10000,"regionType":0},{"id":41857,"lat":0,"lng":0,"name":"毛家皂镇","parentId":-10000,"regionType":0},{"id":41862,"lat":0,"lng":0,"name":"马辛庄乡","parentId":-10000,"regionType":0},{"id":3402,"lat":0,"lng":0,"name":"朔城区","parentId":0,"regionType":0},{"id":3402,"lat":0,"lng":0,"name":"全部朔城区","parentId":3402,"regionType":0},{"id":29645,"lat":0,"lng":0,"name":"平朔路","parentId":3402,"regionType":0},{"id":29646,"lat":0,"lng":0,"name":"金龙商业街","parentId":3402,"regionType":0},{"id":29647,"lat":0,"lng":0,"name":"宝源商务","parentId":3402,"regionType":0},{"id":77229,"lat":0,"lng":0,"name":"中国邮政","parentId":3402,"regionType":0},{"id":77232,"lat":0,"lng":0,"name":"建设银行","parentId":3402,"regionType":0},{"id":77261,"lat":0,"lng":0,"name":"友谊街","parentId":3402,"regionType":0},{"id":77206,"lat":0,"lng":0,"name":"七里河","parentId":3402,"regionType":0},{"id":77251,"lat":0,"lng":0,"name":"民福街","parentId":3402,"regionType":0},{"id":77240,"lat":0,"lng":0,"name":"西环路","parentId":3402,"regionType":0},{"id":3403,"lat":0,"lng":0,"name":"平鲁区","parentId":0,"regionType":0},{"id":3403,"lat":0,"lng":0,"name":"全部平鲁区","parentId":3403,"regionType":0},{"id":-581,"lat":0,"lng":0,"name":"怀仁县","parentId":0,"regionType":0},{"id":-581,"lat":0,"lng":0,"name":"全部怀仁县","parentId":-581,"regionType":0},{"id":41854,"lat":0,"lng":0,"name":"云中镇","parentId":-581,"regionType":0},{"id":41859,"lat":0,"lng":0,"name":"新家园乡","parentId":-581,"regionType":0},{"id":41860,"lat":0,"lng":0,"name":"亲和乡","parentId":-581,"regionType":0},{"id":41857,"lat":0,"lng":0,"name":"毛家皂镇","parentId":-581,"regionType":0},{"id":41862,"lat":0,"lng":0,"name":"马辛庄乡","parentId":-581,"regionType":0},{"id":41856,"lat":0,"lng":0,"name":"金沙滩镇","parentId":-581,"regionType":0},{"id":41863,"lat":0,"lng":0,"name":"河头乡","parentId":-581,"regionType":0},{"id":41861,"lat":0,"lng":0,"name":"海北头乡","parentId":-581,"regionType":0},{"id":41858,"lat":0,"lng":0,"name":"何家堡乡","parentId":-581,"regionType":0},{"id":41855,"lat":0,"lng":0,"name":"吴家窑镇","parentId":-581,"regionType":0},{"id":3407,"lat":0,"lng":0,"name":"怀仁县其他","parentId":-581,"regionType":0},{"id":-578,"lat":0,"lng":0,"name":"山阴县","parentId":0,"regionType":0},{"id":-578,"lat":0,"lng":0,"name":"全部山阴县","parentId":-578,"regionType":0},{"id":41822,"lat":0,"lng":0,"name":"岱岳镇","parentId":-578,"regionType":0},{"id":41831,"lat":0,"lng":0,"name":"马营庄乡","parentId":-578,"regionType":0},{"id":41820,"lat":0,"lng":0,"name":"北周庄镇","parentId":-578,"regionType":0},{"id":41825,"lat":0,"lng":0,"name":"下喇叭乡","parentId":-578,"regionType":0},{"id":41828,"lat":0,"lng":0,"name":"薛圐圙乡","parentId":-578,"regionType":0},{"id":41819,"lat":0,"lng":0,"name":"玉井镇","parentId":-578,"regionType":0},{"id":41821,"lat":0,"lng":0,"name":"古城镇","parentId":-578,"regionType":0},{"id":41826,"lat":0,"lng":0,"name":"合盛堡乡","parentId":-578,"regionType":0},{"id":41829,"lat":0,"lng":0,"name":"后所乡","parentId":-578,"regionType":0},{"id":41830,"lat":0,"lng":0,"name":"张家庄乡","parentId":-578,"regionType":0},{"id":41824,"lat":0,"lng":0,"name":"马营乡","parentId":-578,"regionType":0},{"id":41827,"lat":0,"lng":0,"name":"安荣乡","parentId":-578,"regionType":0},{"id":41823,"lat":0,"lng":0,"name":"吴马营乡","parentId":-578,"regionType":0},{"id":3404,"lat":0,"lng":0,"name":"山阴县其他","parentId":-578,"regionType":0},{"id":-579,"lat":0,"lng":0,"name":"应县","parentId":0,"regionType":0},{"id":-579,"lat":0,"lng":0,"name":"全部应县","parentId":-579,"regionType":0},{"id":41832,"lat":0,"lng":0,"name":"金城镇","parentId":-579,"regionType":0},{"id":41839,"lat":0,"lng":0,"name":"杏寨乡","parentId":-579,"regionType":0},{"id":41836,"lat":0,"lng":0,"name":"义井乡","parentId":-579,"regionType":0},{"id":41842,"lat":0,"lng":0,"name":"大临河乡","parentId":-579,"regionType":0},{"id":41833,"lat":0,"lng":0,"name":"南河种镇","parentId":-579,"regionType":0},{"id":41837,"lat":0,"lng":0,"name":"藏寨乡","parentId":-579,"regionType":0},{"id":41834,"lat":0,"lng":0,"name":"下社镇","parentId":-579,"regionType":0},{"id":41838,"lat":0,"lng":0,"name":"大黄巍乡","parentId":-579,"regionType":0},{"id":41843,"lat":0,"lng":0,"name":"白马石乡","parentId":-579,"regionType":0},{"id":41835,"lat":0,"lng":0,"name":"镇子梁乡","parentId":-579,"regionType":0},{"id":41840,"lat":0,"lng":0,"name":"下马峪乡","parentId":-579,"regionType":0},{"id":41841,"lat":0,"lng":0,"name":"南泉乡","parentId":-579,"regionType":0},{"id":3405,"lat":0,"lng":0,"name":"应县其他","parentId":-579,"regionType":0},{"id":-580,"lat":0,"lng":0,"name":"右玉县","parentId":0,"regionType":0},{"id":-580,"lat":0,"lng":0,"name":"全部右玉县","parentId":-580,"regionType":0},{"id":41844,"lat":0,"lng":0,"name":"新城镇","parentId":-580,"regionType":0},{"id":41847,"lat":0,"lng":0,"name":"元堡子镇","parentId":-580,"regionType":0},{"id":41845,"lat":0,"lng":0,"name":"右卫镇","parentId":-580,"regionType":0},{"id":41846,"lat":0,"lng":0,"name":"威远镇","parentId":-580,"regionType":0},{"id":41848,"lat":0,"lng":0,"name":"牛心堡乡","parentId":-580,"regionType":0},{"id":41849,"lat":0,"lng":0,"name":"白头里乡","parentId":-580,"regionType":0},{"id":41853,"lat":0,"lng":0,"name":"李达窑乡","parentId":-580,"regionType":0},{"id":41850,"lat":0,"lng":0,"name":"高家堡乡","parentId":-580,"regionType":0},{"id":41851,"lat":0,"lng":0,"name":"丁家窑乡","parentId":-580,"regionType":0},{"id":41852,"lat":0,"lng":0,"name":"杨千河乡","parentId":-580,"regionType":0},{"id":3406,"lat":0,"lng":0,"name":"右玉县其他","parentId":-580,"regionType":0}]