[{"id":-10000,"lat":0,"lng":0,"name":"热门商区","parentId":0,"regionType":0},{"id":0,"lat":0,"lng":0,"name":"全部商区","parentId":-10000,"regionType":0},{"id":72389,"lat":0,"lng":0,"name":"新合作购物广场","parentId":-10000,"regionType":0},{"id":76391,"lat":0,"lng":0,"name":"文化古城旅游景区","parentId":-10000,"regionType":0},{"id":76328,"lat":0,"lng":0,"name":"滨州沾化冬枣生态旅游区","parentId":-10000,"regionType":0},{"id":48421,"lat":0,"lng":0,"name":"富源街道","parentId":0,"regionType":0},{"id":48421,"lat":0,"lng":0,"name":"全部富源街道","parentId":48421,"regionType":0},{"id":48425,"lat":0,"lng":0,"name":"泊头镇","parentId":0,"regionType":0},{"id":48425,"lat":0,"lng":0,"name":"全部泊头镇","parentId":48425,"regionType":0},{"id":48420,"lat":0,"lng":0,"name":"富国街道","parentId":0,"regionType":0},{"id":48420,"lat":0,"lng":0,"name":"全部富国街道","parentId":48420,"regionType":0},{"id":48424,"lat":0,"lng":0,"name":"冯家镇","parentId":0,"regionType":0},{"id":48424,"lat":0,"lng":0,"name":"全部冯家镇","parentId":48424,"regionType":0},{"id":4385,"lat":0,"lng":0,"name":"沾化县其他","parentId":0,"regionType":0},{"id":4385,"lat":0,"lng":0,"name":"全部沾化县其他","parentId":4385,"regionType":0},{"id":72389,"lat":0,"lng":0,"name":"新合作购物广场","parentId":4385,"regionType":0},{"id":76391,"lat":0,"lng":0,"name":"文化古城旅游景区","parentId":4385,"regionType":0},{"id":76328,"lat":0,"lng":0,"name":"滨州沾化冬枣生态旅游区","parentId":4385,"regionType":0},{"id":48422,"lat":0,"lng":0,"name":"下洼镇","parentId":0,"regionType":0},{"id":48422,"lat":0,"lng":0,"name":"全部下洼镇","parentId":48422,"regionType":0},{"id":48426,"lat":0,"lng":0,"name":"大高镇","parentId":0,"regionType":0},{"id":48426,"lat":0,"lng":0,"name":"全部大高镇","parentId":48426,"regionType":0},{"id":48423,"lat":0,"lng":0,"name":"古城镇","parentId":0,"regionType":0},{"id":48423,"lat":0,"lng":0,"name":"全部古城镇","parentId":48423,"regionType":0},{"id":48427,"lat":0,"lng":0,"name":"黄升镇","parentId":0,"regionType":0},{"id":48427,"lat":0,"lng":0,"name":"全部黄升镇","parentId":48427,"regionType":0},{"id":48428,"lat":0,"lng":0,"name":"滨海镇","parentId":0,"regionType":0},{"id":48428,"lat":0,"lng":0,"name":"全部滨海镇","parentId":48428,"regionType":0},{"id":48429,"lat":0,"lng":0,"name":"下河乡","parentId":0,"regionType":0},{"id":48429,"lat":0,"lng":0,"name":"全部下河乡","parentId":48429,"regionType":0},{"id":48430,"lat":0,"lng":0,"name":"利国乡","parentId":0,"regionType":0},{"id":48430,"lat":0,"lng":0,"name":"全部利国乡","parentId":48430,"regionType":0}]