[{"id":-10000,"lat":0,"lng":0,"name":"热门商区","parentId":0,"regionType":0},{"id":0,"lat":0,"lng":0,"name":"全部商区","parentId":-10000,"regionType":0},{"id":73616,"lat":0,"lng":0,"name":"湘赣大道","parentId":-10000,"regionType":0},{"id":73618,"lat":0,"lng":0,"name":"义山西路","parentId":-10000,"regionType":0},{"id":73612,"lat":0,"lng":0,"name":"湘赣时代广场","parentId":-10000,"regionType":0},{"id":47753,"lat":0,"lng":0,"name":"三湾乡","parentId":0,"regionType":0},{"id":47753,"lat":0,"lng":0,"name":"全部三湾乡","parentId":47753,"regionType":0},{"id":47738,"lat":0,"lng":0,"name":"禾川镇","parentId":0,"regionType":0},{"id":47738,"lat":0,"lng":0,"name":"全部禾川镇","parentId":47738,"regionType":0},{"id":4267,"lat":0,"lng":0,"name":"永新县其他","parentId":0,"regionType":0},{"id":4267,"lat":0,"lng":0,"name":"全部永新县其他","parentId":4267,"regionType":0},{"id":73616,"lat":0,"lng":0,"name":"湘赣大道","parentId":4267,"regionType":0},{"id":73618,"lat":0,"lng":0,"name":"义山西路","parentId":4267,"regionType":0},{"id":73612,"lat":0,"lng":0,"name":"湘赣时代广场","parentId":4267,"regionType":0},{"id":47742,"lat":0,"lng":0,"name":"龙门镇","parentId":0,"regionType":0},{"id":47742,"lat":0,"lng":0,"name":"全部龙门镇","parentId":47742,"regionType":0},{"id":47740,"lat":0,"lng":0,"name":"龙源口镇","parentId":0,"regionType":0},{"id":47740,"lat":0,"lng":0,"name":"全部龙源口镇","parentId":47740,"regionType":0},{"id":47745,"lat":0,"lng":0,"name":"埠前镇","parentId":0,"regionType":0},{"id":47745,"lat":0,"lng":0,"name":"全部埠前镇","parentId":47745,"regionType":0},{"id":47746,"lat":0,"lng":0,"name":"怀忠镇","parentId":0,"regionType":0},{"id":47746,"lat":0,"lng":0,"name":"全部怀忠镇","parentId":47746,"regionType":0},{"id":47744,"lat":0,"lng":0,"name":"文竹镇","parentId":0,"regionType":0},{"id":47744,"lat":0,"lng":0,"name":"全部文竹镇","parentId":47744,"regionType":0},{"id":47757,"lat":0,"lng":0,"name":"莲洲乡","parentId":0,"regionType":0},{"id":47757,"lat":0,"lng":0,"name":"全部莲洲乡","parentId":47757,"regionType":0},{"id":47759,"lat":0,"lng":0,"name":"象形乡","parentId":0,"regionType":0},{"id":47759,"lat":0,"lng":0,"name":"全部象形乡","parentId":47759,"regionType":0},{"id":47747,"lat":0,"lng":0,"name":"高桥楼镇","parentId":0,"regionType":0},{"id":47747,"lat":0,"lng":0,"name":"全部高桥楼镇","parentId":47747,"regionType":0},{"id":47749,"lat":0,"lng":0,"name":"曲白乡","parentId":0,"regionType":0},{"id":47749,"lat":0,"lng":0,"name":"全部曲白乡","parentId":47749,"regionType":0},{"id":47750,"lat":0,"lng":0,"name":"才丰乡","parentId":0,"regionType":0},{"id":47750,"lat":0,"lng":0,"name":"全部才丰乡","parentId":47750,"regionType":0},{"id":47754,"lat":0,"lng":0,"name":"台岭乡","parentId":0,"regionType":0},{"id":47754,"lat":0,"lng":0,"name":"全部台岭乡","parentId":47754,"regionType":0},{"id":47760,"lat":0,"lng":0,"name":"芦溪乡","parentId":0,"regionType":0},{"id":47760,"lat":0,"lng":0,"name":"全部芦溪乡","parentId":47760,"regionType":0},{"id":47739,"lat":0,"lng":0,"name":"石桥镇","parentId":0,"regionType":0},{"id":47739,"lat":0,"lng":0,"name":"全部石桥镇","parentId":47739,"regionType":0},{"id":47743,"lat":0,"lng":0,"name":"沙市镇","parentId":0,"regionType":0},{"id":47743,"lat":0,"lng":0,"name":"全部沙市镇","parentId":47743,"regionType":0},{"id":47756,"lat":0,"lng":0,"name":"高溪乡","parentId":0,"regionType":0},{"id":47756,"lat":0,"lng":0,"name":"全部高溪乡","parentId":47756,"regionType":0},{"id":47741,"lat":0,"lng":0,"name":"浬田镇","parentId":0,"regionType":0},{"id":47741,"lat":0,"lng":0,"name":"全部浬田镇","parentId":47741,"regionType":0},{"id":47748,"lat":0,"lng":0,"name":"坳南乡","parentId":0,"regionType":0},{"id":47748,"lat":0,"lng":0,"name":"全部坳南乡","parentId":47748,"regionType":0},{"id":47755,"lat":0,"lng":0,"name":"龙田乡","parentId":0,"regionType":0},{"id":47755,"lat":0,"lng":0,"name":"全部龙田乡","parentId":47755,"regionType":0},{"id":47751,"lat":0,"lng":0,"name":"烟阁乡","parentId":0,"regionType":0},{"id":47751,"lat":0,"lng":0,"name":"全部烟阁乡","parentId":47751,"regionType":0},{"id":47752,"lat":0,"lng":0,"name":"在中乡","parentId":0,"regionType":0},{"id":47752,"lat":0,"lng":0,"name":"全部在中乡","parentId":47752,"regionType":0},{"id":47758,"lat":0,"lng":0,"name":"高市乡","parentId":0,"regionType":0},{"id":47758,"lat":0,"lng":0,"name":"全部高市乡","parentId":47758,"regionType":0}]