[{"id":-10000,"lat":0,"lng":0,"name":"热门商区","parentId":0,"regionType":0},{"id":0,"lat":0,"lng":0,"name":"全部商区","parentId":-10000,"regionType":0},{"id":24567,"lat":0,"lng":0,"name":"崇仁县中心城区","parentId":-10000,"regionType":0},{"id":73246,"lat":0,"lng":0,"name":"胜利路","parentId":-10000,"regionType":0},{"id":73240,"lat":0,"lng":0,"name":"人民广场","parentId":-10000,"regionType":0},{"id":73243,"lat":0,"lng":0,"name":"县府西路","parentId":-10000,"regionType":0},{"id":47366,"lat":0,"lng":0,"name":"白鹭乡","parentId":0,"regionType":0},{"id":47366,"lat":0,"lng":0,"name":"全部白鹭乡","parentId":47366,"regionType":0},{"id":47357,"lat":0,"lng":0,"name":"巴山镇","parentId":0,"regionType":0},{"id":47357,"lat":0,"lng":0,"name":"全部巴山镇","parentId":47357,"regionType":0},{"id":4238,"lat":0,"lng":0,"name":"崇仁县其他","parentId":0,"regionType":0},{"id":4238,"lat":0,"lng":0,"name":"全部崇仁县其他","parentId":4238,"regionType":0},{"id":24567,"lat":0,"lng":0,"name":"崇仁县中心城区","parentId":4238,"regionType":0},{"id":73246,"lat":0,"lng":0,"name":"胜利路","parentId":4238,"regionType":0},{"id":73240,"lat":0,"lng":0,"name":"人民广场","parentId":4238,"regionType":0},{"id":73243,"lat":0,"lng":0,"name":"县府西路","parentId":4238,"regionType":0},{"id":47363,"lat":0,"lng":0,"name":"马鞍镇","parentId":0,"regionType":0},{"id":47363,"lat":0,"lng":0,"name":"全部马鞍镇","parentId":47363,"regionType":0},{"id":47365,"lat":0,"lng":0,"name":"六家桥乡","parentId":0,"regionType":0},{"id":47365,"lat":0,"lng":0,"name":"全部六家桥乡","parentId":47365,"regionType":0},{"id":47371,"lat":0,"lng":0,"name":"郭圩乡","parentId":0,"regionType":0},{"id":47371,"lat":0,"lng":0,"name":"全部郭圩乡","parentId":47371,"regionType":0},{"id":47361,"lat":0,"lng":0,"name":"河上镇","parentId":0,"regionType":0},{"id":47361,"lat":0,"lng":0,"name":"全部河上镇","parentId":47361,"regionType":0},{"id":47368,"lat":0,"lng":0,"name":"白陂乡","parentId":0,"regionType":0},{"id":47368,"lat":0,"lng":0,"name":"全部白陂乡","parentId":47368,"regionType":0},{"id":47359,"lat":0,"lng":0,"name":"航埠镇","parentId":0,"regionType":0},{"id":47359,"lat":0,"lng":0,"name":"全部航埠镇","parentId":47359,"regionType":0},{"id":47362,"lat":0,"lng":0,"name":"礼陂镇","parentId":0,"regionType":0},{"id":47362,"lat":0,"lng":0,"name":"全部礼陂镇","parentId":47362,"regionType":0},{"id":47370,"lat":0,"lng":0,"name":"许坊乡","parentId":0,"regionType":0},{"id":47370,"lat":0,"lng":0,"name":"全部许坊乡","parentId":47370,"regionType":0},{"id":47369,"lat":0,"lng":0,"name":"桃源乡","parentId":0,"regionType":0},{"id":47369,"lat":0,"lng":0,"name":"全部桃源乡","parentId":47369,"regionType":0},{"id":47358,"lat":0,"lng":0,"name":"相山镇","parentId":0,"regionType":0},{"id":47358,"lat":0,"lng":0,"name":"全部相山镇","parentId":47358,"regionType":0},{"id":47364,"lat":0,"lng":0,"name":"石庄乡","parentId":0,"regionType":0},{"id":47364,"lat":0,"lng":0,"name":"全部石庄乡","parentId":47364,"regionType":0},{"id":47367,"lat":0,"lng":0,"name":"三山乡","parentId":0,"regionType":0},{"id":47367,"lat":0,"lng":0,"name":"全部三山乡","parentId":47367,"regionType":0},{"id":47360,"lat":0,"lng":0,"name":"孙坊镇","parentId":0,"regionType":0},{"id":47360,"lat":0,"lng":0,"name":"全部孙坊镇","parentId":47360,"regionType":0}]