[{"id":-10000,"lat":0,"lng":0,"name":"热门商区","parentId":0,"regionType":0},{"id":0,"lat":0,"lng":0,"name":"全部商区","parentId":-10000,"regionType":0},{"id":1715,"lat":0,"lng":0,"name":"天一广场","parentId":-10000,"regionType":0},{"id":1716,"lat":0,"lng":0,"name":"鼓楼","parentId":-10000,"regionType":0},{"id":7723,"lat":0,"lng":0,"name":"鄞州万达","parentId":-10000,"regionType":0},{"id":9355,"lat":0,"lng":0,"name":"印象城广场","parentId":-10000,"regionType":0},{"id":1721,"lat":0,"lng":0,"name":"世纪东方广场","parentId":-10000,"regionType":0},{"id":1719,"lat":0,"lng":0,"name":"体育中心","parentId":-10000,"regionType":0},{"id":1720,"lat":0,"lng":0,"name":"彩虹广场","parentId":-10000,"regionType":0},{"id":11373,"lat":0,"lng":0,"name":"来福士","parentId":-10000,"regionType":0},{"id":28412,"lat":0,"lng":0,"name":"南塘老街","parentId":-10000,"regionType":0},{"id":9351,"lat":0,"lng":0,"name":"江北万达","parentId":-10000,"regionType":0},{"id":1717,"lat":0,"lng":0,"name":"西门口","parentId":-10000,"regionType":0},{"id":6037,"lat":0,"lng":0,"name":"月湖公园","parentId":-10000,"regionType":0},{"id":28411,"lat":0,"lng":0,"name":"和义大道","parentId":-10000,"regionType":0},{"id":31113,"lat":0,"lng":0,"name":"环球城","parentId":-10000,"regionType":0},{"id":1722,"lat":0,"lng":0,"name":"老外滩","parentId":-10000,"regionType":0},{"id":28537,"lat":0,"lng":0,"name":"文化广场","parentId":-10000,"regionType":0},{"id":28403,"lat":0,"lng":0,"name":"和丰创意广场","parentId":-10000,"regionType":0},{"id":1718,"lat":0,"lng":0,"name":"翠柏路沿线","parentId":-10000,"regionType":0},{"id":28408,"lat":0,"lng":0,"name":"城隍庙","parentId":-10000,"regionType":0},{"id":64988,"lat":0,"lng":0,"name":"鄞州高教园区","parentId":-10000,"regionType":0},{"id":80,"lat":0,"lng":0,"name":"海曙区","parentId":0,"regionType":0},{"id":80,"lat":0,"lng":0,"name":"全部海曙区","parentId":80,"regionType":0},{"id":1715,"lat":0,"lng":0,"name":"天一广场","parentId":80,"regionType":0},{"id":1716,"lat":0,"lng":0,"name":"鼓楼","parentId":80,"regionType":0},{"id":28412,"lat":0,"lng":0,"name":"南塘老街","parentId":80,"regionType":0},{"id":1717,"lat":0,"lng":0,"name":"西门口","parentId":80,"regionType":0},{"id":6037,"lat":0,"lng":0,"name":"月湖公园","parentId":80,"regionType":0},{"id":28411,"lat":0,"lng":0,"name":"和义大道","parentId":80,"regionType":0},{"id":1718,"lat":0,"lng":0,"name":"翠柏路沿线","parentId":80,"regionType":0},{"id":28408,"lat":0,"lng":0,"name":"城隍庙","parentId":80,"regionType":0},{"id":29947,"lat":0,"lng":0,"name":"高鑫广场","parentId":80,"regionType":0},{"id":28413,"lat":0,"lng":0,"name":"青林湾","parentId":80,"regionType":0},{"id":28414,"lat":0,"lng":0,"name":"汽车南站","parentId":80,"regionType":0},{"id":29948,"lat":0,"lng":0,"name":"恒茂商业广场","parentId":80,"regionType":0},{"id":28418,"lat":0,"lng":0,"name":"联丰路沿线","parentId":80,"regionType":0},{"id":28409,"lat":0,"lng":0,"name":"海曙欧尚","parentId":80,"regionType":0},{"id":28410,"lat":0,"lng":0,"name":"环城西路北段","parentId":80,"regionType":0},{"id":83309,"lat":0,"lng":0,"name":"海曙恒一广场","parentId":80,"regionType":0},{"id":81,"lat":0,"lng":0,"name":"江东区","parentId":0,"regionType":0},{"id":81,"lat":0,"lng":0,"name":"全部江东区","parentId":81,"regionType":0},{"id":1721,"lat":0,"lng":0,"name":"世纪东方广场","parentId":81,"regionType":0},{"id":1719,"lat":0,"lng":0,"name":"体育中心","parentId":81,"regionType":0},{"id":1720,"lat":0,"lng":0,"name":"彩虹广场","parentId":81,"regionType":0},{"id":28537,"lat":0,"lng":0,"name":"文化广场","parentId":81,"regionType":0},{"id":28403,"lat":0,"lng":0,"name":"和丰创意广场","parentId":81,"regionType":0},{"id":28402,"lat":0,"lng":0,"name":"国际会展中心","parentId":81,"regionType":0},{"id":28401,"lat":0,"lng":0,"name":"高新区","parentId":81,"regionType":0},{"id":28538,"lat":0,"lng":0,"name":"百丈东路沿线","parentId":81,"regionType":0},{"id":64919,"lat":0,"lng":0,"name":"港隆广场","parentId":81,"regionType":0},{"id":6038,"lat":0,"lng":0,"name":"兴宁路","parentId":81,"regionType":0},{"id":28404,"lat":0,"lng":0,"name":"宁波书城","parentId":81,"regionType":0},{"id":28399,"lat":0,"lng":0,"name":"滨江商业广场","parentId":81,"regionType":0},{"id":28400,"lat":0,"lng":0,"name":"儿童公园","parentId":81,"regionType":0},{"id":28405,"lat":0,"lng":0,"name":"汽车东站","parentId":81,"regionType":0},{"id":28406,"lat":0,"lng":0,"name":"兴宁时代广场","parentId":81,"regionType":0},{"id":80895,"lat":0,"lng":0,"name":"集盒广场","parentId":81,"regionType":0},{"id":83,"lat":0,"lng":0,"name":"鄞州区","parentId":0,"regionType":0},{"id":83,"lat":0,"lng":0,"name":"全部鄞州区","parentId":83,"regionType":0},{"id":7723,"lat":0,"lng":0,"name":"鄞州万达","parentId":83,"regionType":0},{"id":9355,"lat":0,"lng":0,"name":"印象城广场","parentId":83,"regionType":0},{"id":31113,"lat":0,"lng":0,"name":"环球城","parentId":83,"regionType":0},{"id":64988,"lat":0,"lng":0,"name":"鄞州高教园区","parentId":83,"regionType":0},{"id":28419,"lat":0,"lng":0,"name":"利时百货","parentId":83,"regionType":0},{"id":28420,"lat":0,"lng":0,"name":"南部商务区","parentId":83,"regionType":0},{"id":1725,"lat":0,"lng":0,"name":"东钱湖","parentId":83,"regionType":0},{"id":28422,"lat":0,"lng":0,"name":"舟宿渡","parentId":83,"regionType":0},{"id":1724,"lat":0,"lng":0,"name":"鄞奉路沿线","parentId":83,"regionType":0},{"id":28540,"lat":0,"lng":0,"name":"奥特莱斯广场","parentId":83,"regionType":0},{"id":8953,"lat":0,"lng":0,"name":"轻纺城","parentId":83,"regionType":0},{"id":70194,"lat":0,"lng":0,"name":"方圆中心","parentId":83,"regionType":0},{"id":70515,"lat":0,"lng":0,"name":"东裕商业街","parentId":83,"regionType":0},{"id":28418,"lat":0,"lng":0,"name":"联丰路沿线","parentId":83,"regionType":0},{"id":28417,"lat":0,"lng":0,"name":"明州里","parentId":83,"regionType":0},{"id":28541,"lat":0,"lng":0,"name":"邱隘","parentId":83,"regionType":0},{"id":70322,"lat":0,"lng":0,"name":"巴丽新地广场","parentId":83,"regionType":0},{"id":28415,"lat":0,"lng":0,"name":"创新128广场","parentId":83,"regionType":0},{"id":28421,"lat":0,"lng":0,"name":"培罗城广场","parentId":83,"regionType":0},{"id":28416,"lat":0,"lng":0,"name":"集士港","parentId":83,"regionType":0},{"id":28542,"lat":0,"lng":0,"name":"姜山","parentId":83,"regionType":0},{"id":64987,"lat":0,"lng":0,"name":"五乡","parentId":83,"regionType":0},{"id":67313,"lat":0,"lng":0,"name":"梁祝文化小镇","parentId":83,"regionType":0},{"id":70207,"lat":0,"lng":0,"name":"东方丽都邻里中心","parentId":83,"regionType":0},{"id":70614,"lat":0,"lng":0,"name":"海港城","parentId":83,"regionType":0},{"id":70652,"lat":0,"lng":0,"name":"东部新城银泰城","parentId":83,"regionType":0},{"id":82,"lat":0,"lng":0,"name":"江北区","parentId":0,"regionType":0},{"id":82,"lat":0,"lng":0,"name":"全部江北区","parentId":82,"regionType":0},{"id":11373,"lat":0,"lng":0,"name":"来福士","parentId":82,"regionType":0},{"id":9351,"lat":0,"lng":0,"name":"江北万达","parentId":82,"regionType":0},{"id":1722,"lat":0,"lng":0,"name":"老外滩","parentId":82,"regionType":0},{"id":1723,"lat":0,"lng":0,"name":"大剧院","parentId":82,"regionType":0},{"id":28407,"lat":0,"lng":0,"name":"宁波大学农贸","parentId":82,"regionType":0},{"id":70103,"lat":0,"lng":0,"name":"恒一广场","parentId":82,"regionType":0},{"id":70296,"lat":0,"lng":0,"name":"慈城","parentId":82,"regionType":0},{"id":9357,"lat":0,"lng":0,"name":"日湖公园","parentId":82,"regionType":0},{"id":28539,"lat":0,"lng":0,"name":"洪塘中心","parentId":82,"regionType":0},{"id":417,"lat":0,"lng":0,"name":"北仑区","parentId":0,"regionType":0},{"id":417,"lat":0,"lng":0,"name":"全部北仑区","parentId":417,"regionType":0},{"id":9353,"lat":0,"lng":0,"name":"明州路沿线","parentId":417,"regionType":0},{"id":25313,"lat":0,"lng":0,"name":"北仑银泰城","parentId":417,"regionType":0},{"id":25314,"lat":0,"lng":0,"name":"富邦广场","parentId":417,"regionType":0},{"id":27077,"lat":0,"lng":0,"name":"曼哈顿广场/大润发","parentId":417,"regionType":0},{"id":9354,"lat":0,"lng":0,"name":"新大路沿线","parentId":417,"regionType":0},{"id":25315,"lat":0,"lng":0,"name":"小港街道","parentId":417,"regionType":0},{"id":27061,"lat":0,"lng":0,"name":"嵩山路","parentId":417,"regionType":0},{"id":27063,"lat":0,"lng":0,"name":"大榭","parentId":417,"regionType":0},{"id":25316,"lat":0,"lng":0,"name":"大碶街道","parentId":417,"regionType":0},{"id":27062,"lat":0,"lng":0,"name":"柴桥街道","parentId":417,"regionType":0},{"id":27064,"lat":0,"lng":0,"name":"春晓","parentId":417,"regionType":0},{"id":79869,"lat":0,"lng":0,"name":"博地影秀城","parentId":417,"regionType":0},{"id":-421,"lat":0,"lng":0,"name":"慈溪","parentId":0,"regionType":0},{"id":-421,"lat":0,"lng":0,"name":"全部慈溪","parentId":-421,"regionType":0},{"id":30377,"lat":0,"lng":0,"name":"浒山街道","parentId":-421,"regionType":0},{"id":30372,"lat":0,"lng":0,"name":"观海卫镇","parentId":-421,"regionType":0},{"id":30426,"lat":0,"lng":0,"name":"周巷镇","parentId":-421,"regionType":0},{"id":30412,"lat":0,"lng":0,"name":"逍林镇","parentId":-421,"regionType":0},{"id":65150,"lat":0,"lng":0,"name":"杭州湾新区","parentId":-421,"regionType":0},{"id":30424,"lat":0,"lng":0,"name":"掌起镇","parentId":-421,"regionType":0},{"id":30427,"lat":0,"lng":0,"name":"宗汉街道","parentId":-421,"regionType":0},{"id":24260,"lat":0,"lng":0,"name":"坎墩街道","parentId":-421,"regionType":0},{"id":65151,"lat":0,"lng":0,"name":"龙山镇","parentId":-421,"regionType":0},{"id":30374,"lat":0,"lng":0,"name":"横河镇","parentId":-421,"regionType":0},{"id":30484,"lat":0,"lng":0,"name":"古塘街道","parentId":-421,"regionType":0},{"id":30355,"lat":0,"lng":0,"name":"庵东镇","parentId":-421,"regionType":0},{"id":30386,"lat":0,"lng":0,"name":"匡堰镇","parentId":-421,"regionType":0},{"id":65160,"lat":0,"lng":0,"name":"崇寿镇","parentId":-421,"regionType":0},{"id":65360,"lat":0,"lng":0,"name":"长河镇","parentId":-421,"regionType":0},{"id":65359,"lat":0,"lng":0,"name":"新浦镇","parentId":-421,"regionType":0},{"id":65158,"lat":0,"lng":0,"name":"白沙路街道","parentId":-421,"regionType":0},{"id":65358,"lat":0,"lng":0,"name":"胜山镇","parentId":-421,"regionType":0},{"id":65356,"lat":0,"lng":0,"name":"附海镇","parentId":-421,"regionType":0},{"id":65357,"lat":0,"lng":0,"name":"桥头镇","parentId":-421,"regionType":0},{"id":30459,"lat":0,"lng":0,"name":"其他地区","parentId":-421,"regionType":0},{"id":-423,"lat":0,"lng":0,"name":"余姚","parentId":0,"regionType":0},{"id":-423,"lat":0,"lng":0,"name":"全部余姚","parentId":-423,"regionType":0},{"id":30419,"lat":0,"lng":0,"name":"阳明街道","parentId":-423,"regionType":0},{"id":30367,"lat":0,"lng":0,"name":"凤山街道","parentId":-423,"regionType":0},{"id":30400,"lat":0,"lng":0,"name":"泗门镇","parentId":-423,"regionType":0},{"id":30390,"lat":0,"lng":0,"name":"梨洲街道","parentId":-423,"regionType":0},{"id":30388,"lat":0,"lng":0,"name":"兰江街道","parentId":-423,"regionType":0},{"id":27427,"lat":0,"lng":0,"name":"低塘街道","parentId":-423,"regionType":0},{"id":65374,"lat":0,"lng":0,"name":"马渚镇","parentId":-423,"regionType":0},{"id":65379,"lat":0,"lng":0,"name":"丈亭镇","parentId":-423,"regionType":0},{"id":65372,"lat":0,"lng":0,"name":"陆埠镇","parentId":-423,"regionType":0},{"id":65370,"lat":0,"lng":0,"name":"梁弄镇","parentId":-423,"regionType":0},{"id":65367,"lat":0,"lng":0,"name":"大隐镇","parentId":-423,"regionType":0},{"id":65376,"lat":0,"lng":0,"name":"三七市镇","parentId":-423,"regionType":0},{"id":65369,"lat":0,"lng":0,"name":"黄家埠镇","parentId":-423,"regionType":0},{"id":65371,"lat":0,"lng":0,"name":"临山镇","parentId":-423,"regionType":0},{"id":65375,"lat":0,"lng":0,"name":"牟山镇","parentId":-423,"regionType":0},{"id":65378,"lat":0,"lng":0,"name":"小曹娥镇","parentId":-423,"regionType":0},{"id":65366,"lat":0,"lng":0,"name":"大岚镇","parentId":-423,"regionType":0},{"id":65377,"lat":0,"lng":0,"name":"四明山镇","parentId":-423,"regionType":0},{"id":65368,"lat":0,"lng":0,"name":"河姆渡镇","parentId":-423,"regionType":0},{"id":65373,"lat":0,"lng":0,"name":"鹿亭乡","parentId":-423,"regionType":0},{"id":30461,"lat":0,"lng":0,"name":"其他地区","parentId":-423,"regionType":0},{"id":-2308,"lat":0,"lng":0,"name":"宁海","parentId":0,"regionType":0},{"id":-2308,"lat":0,"lng":0,"name":"全部宁海","parentId":-2308,"regionType":0},{"id":30422,"lat":0,"lng":0,"name":"跃龙街道","parentId":-2308,"regionType":0},{"id":30403,"lat":0,"lng":0,"name":"桃源街道","parentId":-2308,"regionType":0},{"id":30482,"lat":0,"lng":0,"name":"西店镇","parentId":-2308,"regionType":0},{"id":65994,"lat":0,"lng":0,"name":"前童镇","parentId":-2308,"regionType":0},{"id":65989,"lat":0,"lng":0,"name":"岔路镇","parentId":-2308,"regionType":0},{"id":66000,"lat":0,"lng":0,"name":"长街镇","parentId":-2308,"regionType":0},{"id":65997,"lat":0,"lng":0,"name":"深甽镇","parentId":-2308,"regionType":0},{"id":65995,"lat":0,"lng":0,"name":"强蛟镇","parentId":-2308,"regionType":0},{"id":65993,"lat":0,"lng":0,"name":"力洋镇","parentId":-2308,"regionType":0},{"id":65990,"lat":0,"lng":0,"name":"大佳何镇","parentId":-2308,"regionType":0},{"id":65991,"lat":0,"lng":0,"name":"胡陈乡","parentId":-2308,"regionType":0},{"id":65999,"lat":0,"lng":0,"name":"越溪乡","parentId":-2308,"regionType":0},{"id":65988,"lat":0,"lng":0,"name":"茶院乡","parentId":-2308,"regionType":0},{"id":65992,"lat":0,"lng":0,"name":"黄坛镇","parentId":-2308,"regionType":0},{"id":65998,"lat":0,"lng":0,"name":"一市镇","parentId":-2308,"regionType":0},{"id":30465,"lat":0,"lng":0,"name":"其他地区","parentId":-2308,"regionType":0},{"id":-4475,"lat":0,"lng":0,"name":"镇海区","parentId":0,"regionType":0},{"id":-4475,"lat":0,"lng":0,"name":"全部镇海区","parentId":-4475,"regionType":0},{"id":3949,"lat":0,"lng":0,"name":"镇海区","parentId":-4475,"regionType":0},{"id":-422,"lat":0,"lng":0,"name":"奉化","parentId":0,"regionType":0},{"id":-422,"lat":0,"lng":0,"name":"全部奉化","parentId":-422,"regionType":0},{"id":30384,"lat":0,"lng":0,"name":"锦屏街道","parentId":-422,"regionType":0},{"id":30485,"lat":0,"lng":0,"name":"溪口镇","parentId":-422,"regionType":0},{"id":65361,"lat":0,"lng":0,"name":"莼湖镇","parentId":-422,"regionType":0},{"id":65364,"lat":0,"lng":0,"name":"尚田镇","parentId":-422,"regionType":0},{"id":65363,"lat":0,"lng":0,"name":"裘村镇","parentId":-422,"regionType":0},{"id":65362,"lat":0,"lng":0,"name":"大堰镇","parentId":-422,"regionType":0},{"id":30463,"lat":0,"lng":0,"name":"其他地区","parentId":-422,"regionType":0},{"id":-2309,"lat":0,"lng":0,"name":"象山","parentId":0,"regionType":0},{"id":-2309,"lat":0,"lng":0,"name":"全部象山","parentId":-2309,"regionType":0},{"id":31098,"lat":0,"lng":0,"name":"丹西街道","parentId":-2309,"regionType":0},{"id":31101,"lat":0,"lng":0,"name":"石浦镇","parentId":-2309,"regionType":0},{"id":31099,"lat":0,"lng":0,"name":"丹东街道","parentId":-2309,"regionType":0},{"id":31100,"lat":0,"lng":0,"name":"新桥镇","parentId":-2309,"regionType":0},{"id":66011,"lat":0,"lng":0,"name":"西周镇","parentId":-2309,"regionType":0},{"id":66002,"lat":0,"lng":0,"name":"定塘镇","parentId":-2309,"regionType":0},{"id":66003,"lat":0,"lng":0,"name":"东陈乡","parentId":-2309,"regionType":0},{"id":66008,"lat":0,"lng":0,"name":"墙头镇","parentId":-2309,"regionType":0},{"id":66005,"lat":0,"lng":0,"name":"鹤浦镇","parentId":-2309,"regionType":0},{"id":66007,"lat":0,"lng":0,"name":"茅洋乡","parentId":-2309,"regionType":0},{"id":66010,"lat":0,"lng":0,"name":"涂茨镇","parentId":-2309,"regionType":0},{"id":66001,"lat":0,"lng":0,"name":"大徐镇","parentId":-2309,"regionType":0},{"id":66004,"lat":0,"lng":0,"name":"高塘岛乡","parentId":-2309,"regionType":0},{"id":66012,"lat":0,"lng":0,"name":"贤庠镇","parentId":-2309,"regionType":0},{"id":66009,"lat":0,"lng":0,"name":"泗洲头镇","parentId":-2309,"regionType":0},{"id":66006,"lat":0,"lng":0,"name":"黄避岙乡","parentId":-2309,"regionType":0},{"id":66013,"lat":0,"lng":0,"name":"晓塘乡","parentId":-2309,"regionType":0},{"id":27664,"lat":0,"lng":0,"name":"其他地区","parentId":-2309,"regionType":0}]