[{"id":-10000,"lat":0,"lng":0,"name":"热门商区","parentId":0,"regionType":0},{"id":0,"lat":0,"lng":0,"name":"全部商区","parentId":-10000,"regionType":0},{"id":64886,"lat":0,"lng":0,"name":"新建路","parentId":-10000,"regionType":0},{"id":65219,"lat":0,"lng":0,"name":"高新区","parentId":-10000,"regionType":0},{"id":29052,"lat":0,"lng":0,"name":"经二路","parentId":-10000,"regionType":0},{"id":29053,"lat":0,"lng":0,"name":"火炬路","parentId":-10000,"regionType":0},{"id":29041,"lat":0,"lng":0,"name":"虢镇","parentId":-10000,"regionType":0},{"id":29044,"lat":0,"lng":0,"name":"第五大道","parentId":-10000,"regionType":0},{"id":29047,"lat":0,"lng":0,"name":"体育场","parentId":-10000,"regionType":0},{"id":29043,"lat":0,"lng":0,"name":"东风路","parentId":-10000,"regionType":0},{"id":29049,"lat":0,"lng":0,"name":"清姜路沿线","parentId":-10000,"regionType":0},{"id":64888,"lat":0,"lng":0,"name":"太阳市","parentId":-10000,"regionType":0},{"id":29051,"lat":0,"lng":0,"name":"经一路","parentId":-10000,"regionType":0},{"id":66408,"lat":0,"lng":0,"name":"行政中心","parentId":-10000,"regionType":0},{"id":29054,"lat":0,"lng":0,"name":"火车站周边","parentId":-10000,"regionType":0},{"id":29042,"lat":0,"lng":0,"name":"金台大道","parentId":-10000,"regionType":0},{"id":29046,"lat":0,"lng":0,"name":"英达路","parentId":-10000,"regionType":0},{"id":29050,"lat":0,"lng":0,"name":"开元商城","parentId":-10000,"regionType":0},{"id":29055,"lat":0,"lng":0,"name":"公园路","parentId":-10000,"regionType":0},{"id":64889,"lat":0,"lng":0,"name":"豪城","parentId":-10000,"regionType":0},{"id":64887,"lat":0,"lng":0,"name":"姜谭路","parentId":-10000,"regionType":0},{"id":29040,"lat":0,"lng":0,"name":"行政中心","parentId":-10000,"regionType":0},{"id":5461,"lat":0,"lng":0,"name":"渭滨区","parentId":0,"regionType":0},{"id":5461,"lat":0,"lng":0,"name":"全部渭滨区","parentId":5461,"regionType":0},{"id":64886,"lat":0,"lng":0,"name":"新建路","parentId":5461,"regionType":0},{"id":65219,"lat":0,"lng":0,"name":"高新区","parentId":5461,"regionType":0},{"id":29052,"lat":0,"lng":0,"name":"经二路","parentId":5461,"regionType":0},{"id":29053,"lat":0,"lng":0,"name":"火炬路","parentId":5461,"regionType":0},{"id":29047,"lat":0,"lng":0,"name":"体育场","parentId":5461,"regionType":0},{"id":29049,"lat":0,"lng":0,"name":"清姜路沿线","parentId":5461,"regionType":0},{"id":64888,"lat":0,"lng":0,"name":"太阳市","parentId":5461,"regionType":0},{"id":29051,"lat":0,"lng":0,"name":"经一路","parentId":5461,"regionType":0},{"id":29054,"lat":0,"lng":0,"name":"火车站周边","parentId":5461,"regionType":0},{"id":29046,"lat":0,"lng":0,"name":"英达路","parentId":5461,"regionType":0},{"id":29050,"lat":0,"lng":0,"name":"开元商城","parentId":5461,"regionType":0},{"id":29055,"lat":0,"lng":0,"name":"公园路","parentId":5461,"regionType":0},{"id":64887,"lat":0,"lng":0,"name":"姜谭路","parentId":5461,"regionType":0},{"id":29048,"lat":0,"lng":0,"name":"人民公园","parentId":5461,"regionType":0},{"id":5462,"lat":0,"lng":0,"name":"金台区","parentId":0,"regionType":0},{"id":5462,"lat":0,"lng":0,"name":"全部金台区","parentId":5462,"regionType":0},{"id":29044,"lat":0,"lng":0,"name":"第五大道","parentId":5462,"regionType":0},{"id":29043,"lat":0,"lng":0,"name":"东风路","parentId":5462,"regionType":0},{"id":66408,"lat":0,"lng":0,"name":"行政中心","parentId":5462,"regionType":0},{"id":29042,"lat":0,"lng":0,"name":"金台大道","parentId":5462,"regionType":0},{"id":64889,"lat":0,"lng":0,"name":"豪城","parentId":5462,"regionType":0},{"id":5463,"lat":0,"lng":0,"name":"陈仓区","parentId":0,"regionType":0},{"id":5463,"lat":0,"lng":0,"name":"全部陈仓区","parentId":5463,"regionType":0},{"id":29041,"lat":0,"lng":0,"name":"虢镇","parentId":5463,"regionType":0},{"id":29040,"lat":0,"lng":0,"name":"行政中心","parentId":5463,"regionType":0},{"id":-2043,"lat":0,"lng":0,"name":"岐山县","parentId":0,"regionType":0},{"id":-2043,"lat":0,"lng":0,"name":"全部岐山县","parentId":-2043,"regionType":0},{"id":60508,"lat":0,"lng":0,"name":"蔡家坡镇","parentId":-2043,"regionType":0},{"id":60507,"lat":0,"lng":0,"name":"凤鸣镇","parentId":-2043,"regionType":0},{"id":60512,"lat":0,"lng":0,"name":"青化镇","parentId":-2043,"regionType":0},{"id":60513,"lat":0,"lng":0,"name":"枣林镇","parentId":-2043,"regionType":0},{"id":60514,"lat":0,"lng":0,"name":"雍川镇","parentId":-2043,"regionType":0},{"id":60511,"lat":0,"lng":0,"name":"祝家庄镇","parentId":-2043,"regionType":0},{"id":60509,"lat":0,"lng":0,"name":"益店镇","parentId":-2043,"regionType":0},{"id":60510,"lat":0,"lng":0,"name":"蒲村镇","parentId":-2043,"regionType":0},{"id":60515,"lat":0,"lng":0,"name":"故郡镇","parentId":-2043,"regionType":0},{"id":60516,"lat":0,"lng":0,"name":"京当镇","parentId":-2043,"regionType":0},{"id":5465,"lat":0,"lng":0,"name":"岐山县其他","parentId":-2043,"regionType":0},{"id":-2045,"lat":0,"lng":0,"name":"眉县","parentId":0,"regionType":0},{"id":-2045,"lat":0,"lng":0,"name":"全部眉县","parentId":-2045,"regionType":0},{"id":60525,"lat":0,"lng":0,"name":"首善镇","parentId":-2045,"regionType":0},{"id":60528,"lat":0,"lng":0,"name":"汤峪镇","parentId":-2045,"regionType":0},{"id":60529,"lat":0,"lng":0,"name":"常兴镇","parentId":-2045,"regionType":0},{"id":60526,"lat":0,"lng":0,"name":"横渠镇","parentId":-2045,"regionType":0},{"id":60531,"lat":0,"lng":0,"name":"营头镇","parentId":-2045,"regionType":0},{"id":60527,"lat":0,"lng":0,"name":"槐芽镇","parentId":-2045,"regionType":0},{"id":60530,"lat":0,"lng":0,"name":"金渠镇","parentId":-2045,"regionType":0},{"id":60532,"lat":0,"lng":0,"name":"齐镇","parentId":-2045,"regionType":0},{"id":5467,"lat":0,"lng":0,"name":"眉县其他","parentId":-2045,"regionType":0},{"id":-2042,"lat":0,"lng":0,"name":"凤翔县","parentId":0,"regionType":0},{"id":-2042,"lat":0,"lng":0,"name":"全部凤翔县","parentId":-2042,"regionType":0},{"id":60495,"lat":0,"lng":0,"name":"城关镇","parentId":-2042,"regionType":0},{"id":60496,"lat":0,"lng":0,"name":"虢王镇","parentId":-2042,"regionType":0},{"id":60504,"lat":0,"lng":0,"name":"柳林镇","parentId":-2042,"regionType":0},{"id":60498,"lat":0,"lng":0,"name":"横水镇","parentId":-2042,"regionType":0},{"id":60501,"lat":0,"lng":0,"name":"南指挥镇","parentId":-2042,"regionType":0},{"id":60497,"lat":0,"lng":0,"name":"彪角镇","parentId":-2042,"regionType":0},{"id":60500,"lat":0,"lng":0,"name":"糜杆桥镇","parentId":-2042,"regionType":0},{"id":60502,"lat":0,"lng":0,"name":"陈村镇","parentId":-2042,"regionType":0},{"id":60503,"lat":0,"lng":0,"name":"长青镇","parentId":-2042,"regionType":0},{"id":60499,"lat":0,"lng":0,"name":"田家庄镇","parentId":-2042,"regionType":0},{"id":60505,"lat":0,"lng":0,"name":"姚家沟镇","parentId":-2042,"regionType":0},{"id":60506,"lat":0,"lng":0,"name":"范家寨镇","parentId":-2042,"regionType":0},{"id":5464,"lat":0,"lng":0,"name":"凤翔县其他","parentId":-2042,"regionType":0},{"id":-2044,"lat":0,"lng":0,"name":"扶风县","parentId":0,"regionType":0},{"id":-2044,"lat":0,"lng":0,"name":"全部扶风县","parentId":-2044,"regionType":0},{"id":60524,"lat":0,"lng":0,"name":"法门镇","parentId":-2044,"regionType":0},{"id":60517,"lat":0,"lng":0,"name":"城关镇","parentId":-2044,"regionType":0},{"id":60523,"lat":0,"lng":0,"name":"召公镇","parentId":-2044,"regionType":0},{"id":60520,"lat":0,"lng":0,"name":"绛帐镇","parentId":-2044,"regionType":0},{"id":60521,"lat":0,"lng":0,"name":"段家镇","parentId":-2044,"regionType":0},{"id":60518,"lat":0,"lng":0,"name":"天度镇","parentId":-2044,"regionType":0},{"id":60522,"lat":0,"lng":0,"name":"杏林镇","parentId":-2044,"regionType":0},{"id":60519,"lat":0,"lng":0,"name":"午井镇","parentId":-2044,"regionType":0},{"id":5466,"lat":0,"lng":0,"name":"扶风县其他","parentId":-2044,"regionType":0},{"id":-2046,"lat":0,"lng":0,"name":"陇县","parentId":0,"regionType":0},{"id":-2046,"lat":0,"lng":0,"name":"全部陇县","parentId":-2046,"regionType":0},{"id":60533,"lat":0,"lng":0,"name":"城关镇","parentId":-2046,"regionType":0},{"id":60538,"lat":0,"lng":0,"name":"天成镇","parentId":-2046,"regionType":0},{"id":60536,"lat":0,"lng":0,"name":"东南镇","parentId":-2046,"regionType":0},{"id":60534,"lat":0,"lng":0,"name":"东风镇","parentId":-2046,"regionType":0},{"id":60541,"lat":0,"lng":0,"name":"火烧寨镇","parentId":-2046,"regionType":0},{"id":60539,"lat":0,"lng":0,"name":"曹家湾镇","parentId":-2046,"regionType":0},{"id":60542,"lat":0,"lng":0,"name":"李家河镇","parentId":-2046,"regionType":0},{"id":60535,"lat":0,"lng":0,"name":"八渡镇","parentId":-2046,"regionType":0},{"id":60537,"lat":0,"lng":0,"name":"温水镇","parentId":-2046,"regionType":0},{"id":60540,"lat":0,"lng":0,"name":"固关镇","parentId":-2046,"regionType":0},{"id":60544,"lat":0,"lng":0,"name":"新集川镇","parentId":-2046,"regionType":0},{"id":60543,"lat":0,"lng":0,"name":"河北镇","parentId":-2046,"regionType":0},{"id":5468,"lat":0,"lng":0,"name":"陇县其他","parentId":-2046,"regionType":0},{"id":-2049,"lat":0,"lng":0,"name":"凤县","parentId":0,"regionType":0},{"id":-2049,"lat":0,"lng":0,"name":"全部凤县","parentId":-2049,"regionType":0},{"id":60560,"lat":0,"lng":0,"name":"双石铺镇","parentId":-2049,"regionType":0},{"id":60561,"lat":0,"lng":0,"name":"凤州镇","parentId":-2049,"regionType":0},{"id":60562,"lat":0,"lng":0,"name":"黄牛铺镇","parentId":-2049,"regionType":0},{"id":60564,"lat":0,"lng":0,"name":"河口镇","parentId":-2049,"regionType":0},{"id":60565,"lat":0,"lng":0,"name":"唐藏镇","parentId":-2049,"regionType":0},{"id":60566,"lat":0,"lng":0,"name":"平木镇","parentId":-2049,"regionType":0},{"id":60563,"lat":0,"lng":0,"name":"红花铺镇","parentId":-2049,"regionType":0},{"id":60568,"lat":0,"lng":0,"name":"留凤关镇","parentId":-2049,"regionType":0},{"id":5471,"lat":0,"lng":0,"name":"凤县其他","parentId":-2049,"regionType":0},{"id":-2047,"lat":0,"lng":0,"name":"千阳县","parentId":0,"regionType":0},{"id":-2047,"lat":0,"lng":0,"name":"全部千阳县","parentId":-2047,"regionType":0},{"id":60545,"lat":0,"lng":0,"name":"城关镇","parentId":-2047,"regionType":0},{"id":60548,"lat":0,"lng":0,"name":"张家塬镇","parentId":-2047,"regionType":0},{"id":60549,"lat":0,"lng":0,"name":"水沟镇","parentId":-2047,"regionType":0},{"id":60550,"lat":0,"lng":0,"name":"草碧镇","parentId":-2047,"regionType":0},{"id":60547,"lat":0,"lng":0,"name":"南寨镇","parentId":-2047,"regionType":0},{"id":60551,"lat":0,"lng":0,"name":"柿沟镇","parentId":-2047,"regionType":0},{"id":60552,"lat":0,"lng":0,"name":"高崖镇","parentId":-2047,"regionType":0},{"id":60546,"lat":0,"lng":0,"name":"崔家头镇","parentId":-2047,"regionType":0},{"id":5469,"lat":0,"lng":0,"name":"千阳县其他","parentId":-2047,"regionType":0},{"id":-2048,"lat":0,"lng":0,"name":"麟游县","parentId":0,"regionType":0},{"id":-2048,"lat":0,"lng":0,"name":"全部麟游县","parentId":-2048,"regionType":0},{"id":60553,"lat":0,"lng":0,"name":"九成宫镇","parentId":-2048,"regionType":0},{"id":60555,"lat":0,"lng":0,"name":"招贤镇","parentId":-2048,"regionType":0},{"id":60556,"lat":0,"lng":0,"name":"两亭镇","parentId":-2048,"regionType":0},{"id":60554,"lat":0,"lng":0,"name":"崔木镇","parentId":-2048,"regionType":0},{"id":60557,"lat":0,"lng":0,"name":"常丰镇","parentId":-2048,"regionType":0},{"id":60558,"lat":0,"lng":0,"name":"丈八镇","parentId":-2048,"regionType":0},{"id":60559,"lat":0,"lng":0,"name":"酒房镇","parentId":-2048,"regionType":0},{"id":5470,"lat":0,"lng":0,"name":"麟游县其他","parentId":-2048,"regionType":0},{"id":-2050,"lat":0,"lng":0,"name":"太白县","parentId":0,"regionType":0},{"id":-2050,"lat":0,"lng":0,"name":"全部太白县","parentId":-2050,"regionType":0},{"id":60569,"lat":0,"lng":0,"name":"咀头镇","parentId":-2050,"regionType":0},{"id":60571,"lat":0,"lng":0,"name":"鹦鸽镇","parentId":-2050,"regionType":0},{"id":60573,"lat":0,"lng":0,"name":"太白河镇","parentId":-2050,"regionType":0},{"id":60574,"lat":0,"lng":0,"name":"黄柏塬镇","parentId":-2050,"regionType":0},{"id":60570,"lat":0,"lng":0,"name":"桃川镇","parentId":-2050,"regionType":0},{"id":60572,"lat":0,"lng":0,"name":"靖口镇","parentId":-2050,"regionType":0},{"id":5472,"lat":0,"lng":0,"name":"太白县其他","parentId":-2050,"regionType":0}]