[{"id":-10000,"lat":0,"lng":0,"name":"热门商区","parentId":0,"regionType":0},{"id":0,"lat":0,"lng":0,"name":"全部商区","parentId":-10000,"regionType":0},{"id":59892,"lat":0,"lng":0,"name":"协格尔镇","parentId":0,"regionType":0},{"id":59892,"lat":0,"lng":0,"name":"全部协格尔镇","parentId":59892,"regionType":0},{"id":5390,"lat":0,"lng":0,"name":"定日县其他","parentId":0,"regionType":0},{"id":5390,"lat":0,"lng":0,"name":"全部定日县其他","parentId":5390,"regionType":0},{"id":59900,"lat":0,"lng":0,"name":"扎西宗乡","parentId":0,"regionType":0},{"id":59900,"lat":0,"lng":0,"name":"全部扎西宗乡","parentId":59900,"regionType":0},{"id":59896,"lat":0,"lng":0,"name":"尼辖乡","parentId":0,"regionType":0},{"id":59896,"lat":0,"lng":0,"name":"全部尼辖乡","parentId":59896,"regionType":0},{"id":59893,"lat":0,"lng":0,"name":"岗嘎镇","parentId":0,"regionType":0},{"id":59893,"lat":0,"lng":0,"name":"全部岗嘎镇","parentId":59893,"regionType":0},{"id":59898,"lat":0,"lng":0,"name":"曲当乡","parentId":0,"regionType":0},{"id":59898,"lat":0,"lng":0,"name":"全部曲当乡","parentId":59898,"regionType":0},{"id":59894,"lat":0,"lng":0,"name":"加措乡","parentId":0,"regionType":0},{"id":59894,"lat":0,"lng":0,"name":"全部加措乡","parentId":59894,"regionType":0},{"id":59899,"lat":0,"lng":0,"name":"扎果乡","parentId":0,"regionType":0},{"id":59899,"lat":0,"lng":0,"name":"全部扎果乡","parentId":59899,"regionType":0},{"id":59903,"lat":0,"lng":0,"name":"措果乡","parentId":0,"regionType":0},{"id":59903,"lat":0,"lng":0,"name":"全部措果乡","parentId":59903,"regionType":0},{"id":59904,"lat":0,"lng":0,"name":"克玛乡","parentId":0,"regionType":0},{"id":59904,"lat":0,"lng":0,"name":"全部克玛乡","parentId":59904,"regionType":0}]