[{"id":-10000,"lat":0,"lng":0,"name":"热门商区","parentId":0,"regionType":0},{"id":0,"lat":0,"lng":0,"name":"全部商区","parentId":-10000,"regionType":0},{"id":72098,"lat":0,"lng":0,"name":"大学城","parentId":-10000,"regionType":0},{"id":79471,"lat":0,"lng":0,"name":"淮口镇","parentId":-10000,"regionType":0},{"id":72103,"lat":0,"lng":0,"name":"车站","parentId":-10000,"regionType":0},{"id":79468,"lat":0,"lng":0,"name":"金泉路","parentId":-10000,"regionType":0},{"id":79469,"lat":0,"lng":0,"name":"万方街","parentId":-10000,"regionType":0},{"id":72099,"lat":0,"lng":0,"name":"康宁路","parentId":-10000,"regionType":0},{"id":72102,"lat":0,"lng":0,"name":"耍都","parentId":-10000,"regionType":0},{"id":53707,"lat":0,"lng":0,"name":"云合镇","parentId":0,"regionType":0},{"id":53707,"lat":0,"lng":0,"name":"全部云合镇","parentId":53707,"regionType":0},{"id":53706,"lat":0,"lng":0,"name":"土桥镇","parentId":0,"regionType":0},{"id":53706,"lat":0,"lng":0,"name":"全部土桥镇","parentId":53706,"regionType":0},{"id":53702,"lat":0,"lng":0,"name":"竹篙镇","parentId":0,"regionType":0},{"id":53702,"lat":0,"lng":0,"name":"全部竹篙镇","parentId":53702,"regionType":0},{"id":53698,"lat":0,"lng":0,"name":"三溪镇","parentId":0,"regionType":0},{"id":53698,"lat":0,"lng":0,"name":"全部三溪镇","parentId":53698,"regionType":0},{"id":53696,"lat":0,"lng":0,"name":"五凤镇","parentId":0,"regionType":0},{"id":53696,"lat":0,"lng":0,"name":"全部五凤镇","parentId":53696,"regionType":0},{"id":53690,"lat":0,"lng":0,"name":"赵镇街道","parentId":0,"regionType":0},{"id":53690,"lat":0,"lng":0,"name":"全部赵镇街道","parentId":53690,"regionType":0},{"id":53708,"lat":0,"lng":0,"name":"又新镇","parentId":0,"regionType":0},{"id":53708,"lat":0,"lng":0,"name":"全部又新镇","parentId":53708,"regionType":0},{"id":53694,"lat":0,"lng":0,"name":"淮口镇","parentId":0,"regionType":0},{"id":53694,"lat":0,"lng":0,"name":"全部淮口镇","parentId":53694,"regionType":0},{"id":53691,"lat":0,"lng":0,"name":"三星镇","parentId":0,"regionType":0},{"id":53691,"lat":0,"lng":0,"name":"全部三星镇","parentId":53691,"regionType":0},{"id":53697,"lat":0,"lng":0,"name":"高板镇","parentId":0,"regionType":0},{"id":53697,"lat":0,"lng":0,"name":"全部高板镇","parentId":53697,"regionType":0},{"id":53692,"lat":0,"lng":0,"name":"清江镇","parentId":0,"regionType":0},{"id":53692,"lat":0,"lng":0,"name":"全部清江镇","parentId":53692,"regionType":0},{"id":27624,"lat":0,"lng":0,"name":"金堂县其他","parentId":0,"regionType":0},{"id":27624,"lat":0,"lng":0,"name":"全部金堂县其他","parentId":27624,"regionType":0},{"id":72098,"lat":0,"lng":0,"name":"大学城","parentId":27624,"regionType":0},{"id":79471,"lat":0,"lng":0,"name":"淮口镇","parentId":27624,"regionType":0},{"id":72103,"lat":0,"lng":0,"name":"车站","parentId":27624,"regionType":0},{"id":79468,"lat":0,"lng":0,"name":"金泉路","parentId":27624,"regionType":0},{"id":79469,"lat":0,"lng":0,"name":"万方街","parentId":27624,"regionType":0},{"id":72099,"lat":0,"lng":0,"name":"康宁路","parentId":27624,"regionType":0},{"id":72102,"lat":0,"lng":0,"name":"耍都","parentId":27624,"regionType":0},{"id":53701,"lat":0,"lng":0,"name":"赵家镇","parentId":0,"regionType":0},{"id":53701,"lat":0,"lng":0,"name":"全部赵家镇","parentId":53701,"regionType":0},{"id":53695,"lat":0,"lng":0,"name":"白果镇","parentId":0,"regionType":0},{"id":53695,"lat":0,"lng":0,"name":"全部白果镇","parentId":53695,"regionType":0},{"id":53704,"lat":0,"lng":0,"name":"隆盛镇","parentId":0,"regionType":0},{"id":53704,"lat":0,"lng":0,"name":"全部隆盛镇","parentId":53704,"regionType":0},{"id":53693,"lat":0,"lng":0,"name":"官仓镇","parentId":0,"regionType":0},{"id":53693,"lat":0,"lng":0,"name":"全部官仓镇","parentId":53693,"regionType":0},{"id":53703,"lat":0,"lng":0,"name":"广兴镇","parentId":0,"regionType":0},{"id":53703,"lat":0,"lng":0,"name":"全部广兴镇","parentId":53703,"regionType":0},{"id":53705,"lat":0,"lng":0,"name":"转龙镇","parentId":0,"regionType":0},{"id":53705,"lat":0,"lng":0,"name":"全部转龙镇","parentId":53705,"regionType":0},{"id":53709,"lat":0,"lng":0,"name":"栖贤乡","parentId":0,"regionType":0},{"id":53709,"lat":0,"lng":0,"name":"全部栖贤乡","parentId":53709,"regionType":0},{"id":53700,"lat":0,"lng":0,"name":"金龙镇","parentId":0,"regionType":0},{"id":53700,"lat":0,"lng":0,"name":"全部金龙镇","parentId":53700,"regionType":0},{"id":53699,"lat":0,"lng":0,"name":"福兴镇","parentId":0,"regionType":0},{"id":53699,"lat":0,"lng":0,"name":"全部福兴镇","parentId":53699,"regionType":0},{"id":53710,"lat":0,"lng":0,"name":"平桥乡","parentId":0,"regionType":0},{"id":53710,"lat":0,"lng":0,"name":"全部平桥乡","parentId":53710,"regionType":0}]