[{"id":-10000,"lat":0,"lng":0,"name":"热门商区","parentId":0,"regionType":0},{"id":0,"lat":0,"lng":0,"name":"全部商区","parentId":-10000,"regionType":0},{"id":73742,"lat":0,"lng":0,"name":"凤凰大厦","parentId":-10000,"regionType":0},{"id":73754,"lat":0,"lng":0,"name":"平安购物","parentId":-10000,"regionType":0},{"id":73748,"lat":0,"lng":0,"name":"鑫海洋购物商城","parentId":-10000,"regionType":0},{"id":57173,"lat":0,"lng":0,"name":"龙泉镇","parentId":0,"regionType":0},{"id":57173,"lat":0,"lng":0,"name":"全部龙泉镇","parentId":57173,"regionType":0},{"id":5148,"lat":0,"lng":0,"name":"凤冈县其他","parentId":0,"regionType":0},{"id":5148,"lat":0,"lng":0,"name":"全部凤冈县其他","parentId":5148,"regionType":0},{"id":73742,"lat":0,"lng":0,"name":"凤凰大厦","parentId":5148,"regionType":0},{"id":73754,"lat":0,"lng":0,"name":"平安购物","parentId":5148,"regionType":0},{"id":73748,"lat":0,"lng":0,"name":"鑫海洋购物商城","parentId":5148,"regionType":0},{"id":57185,"lat":0,"lng":0,"name":"石径乡","parentId":0,"regionType":0},{"id":57185,"lat":0,"lng":0,"name":"全部石径乡","parentId":57185,"regionType":0},{"id":57182,"lat":0,"lng":0,"name":"何坝乡","parentId":0,"regionType":0},{"id":57182,"lat":0,"lng":0,"name":"全部何坝乡","parentId":57182,"regionType":0},{"id":57178,"lat":0,"lng":0,"name":"花坪镇","parentId":0,"regionType":0},{"id":57178,"lat":0,"lng":0,"name":"全部花坪镇","parentId":57178,"regionType":0},{"id":57179,"lat":0,"lng":0,"name":"绥阳镇","parentId":0,"regionType":0},{"id":57179,"lat":0,"lng":0,"name":"全部绥阳镇","parentId":57179,"regionType":0},{"id":57174,"lat":0,"lng":0,"name":"进化镇","parentId":0,"regionType":0},{"id":57174,"lat":0,"lng":0,"name":"全部进化镇","parentId":57174,"regionType":0},{"id":57177,"lat":0,"lng":0,"name":"永和镇","parentId":0,"regionType":0},{"id":57177,"lat":0,"lng":0,"name":"全部永和镇","parentId":57177,"regionType":0},{"id":57180,"lat":0,"lng":0,"name":"土溪镇","parentId":0,"regionType":0},{"id":57180,"lat":0,"lng":0,"name":"全部土溪镇","parentId":57180,"regionType":0},{"id":57176,"lat":0,"lng":0,"name":"蜂岩镇","parentId":0,"regionType":0},{"id":57176,"lat":0,"lng":0,"name":"全部蜂岩镇","parentId":57176,"regionType":0},{"id":57181,"lat":0,"lng":0,"name":"永安镇","parentId":0,"regionType":0},{"id":57181,"lat":0,"lng":0,"name":"全部永安镇","parentId":57181,"regionType":0},{"id":57186,"lat":0,"lng":0,"name":"新建乡","parentId":0,"regionType":0},{"id":57186,"lat":0,"lng":0,"name":"全部新建乡","parentId":57186,"regionType":0},{"id":57175,"lat":0,"lng":0,"name":"琊川镇","parentId":0,"regionType":0},{"id":57175,"lat":0,"lng":0,"name":"全部琊川镇","parentId":57175,"regionType":0},{"id":57184,"lat":0,"lng":0,"name":"王寨乡","parentId":0,"regionType":0},{"id":57184,"lat":0,"lng":0,"name":"全部王寨乡","parentId":57184,"regionType":0},{"id":57183,"lat":0,"lng":0,"name":"天桥乡","parentId":0,"regionType":0},{"id":57183,"lat":0,"lng":0,"name":"全部天桥乡","parentId":57183,"regionType":0}]