[{"id":-10000,"lat":0,"lng":0,"name":"热门商区","parentId":0,"regionType":0},{"id":0,"lat":0,"lng":0,"name":"全部商区","parentId":-10000,"regionType":0},{"id":83276,"lat":0,"lng":0,"name":"阿洛纳海滩","parentId":-10000,"regionType":0},{"id":83275,"lat":0,"lng":0,"name":"塔比拉兰市中心","parentId":-10000,"regionType":0},{"id":83274,"lat":0,"lng":0,"name":"塔比拉兰机场","parentId":-10000,"regionType":0},{"id":83277,"lat":0,"lng":0,"name":"杜马伦海滩","parentId":-10000,"regionType":0},{"id":83282,"lat":0,"lng":0,"name":"塔比拉兰码头","parentId":-10000,"regionType":0},{"id":83278,"lat":0,"lng":0,"name":"蜜蜂农场","parentId":-10000,"regionType":0},{"id":83280,"lat":0,"lng":0,"name":"ICM商场","parentId":-10000,"regionType":0},{"id":83279,"lat":0,"lng":0,"name":"眼镜猴保护中心","parentId":-10000,"regionType":0},{"id":83271,"lat":0,"lng":0,"name":"商区","parentId":0,"regionType":0},{"id":83271,"lat":0,"lng":0,"name":"全部商区","parentId":83271,"regionType":0},{"id":83276,"lat":0,"lng":0,"name":"阿洛纳海滩","parentId":83271,"regionType":0},{"id":83275,"lat":0,"lng":0,"name":"塔比拉兰市中心","parentId":83271,"regionType":0},{"id":83274,"lat":0,"lng":0,"name":"塔比拉兰机场","parentId":83271,"regionType":0},{"id":83277,"lat":0,"lng":0,"name":"杜马伦海滩","parentId":83271,"regionType":0},{"id":83273,"lat":0,"lng":0,"name":"机场车站","parentId":0,"regionType":0},{"id":83273,"lat":0,"lng":0,"name":"全部机场车站","parentId":83273,"regionType":0},{"id":83282,"lat":0,"lng":0,"name":"塔比拉兰码头","parentId":83273,"regionType":0},{"id":83281,"lat":0,"lng":0,"name":"塔比拉兰机场","parentId":83273,"regionType":0},{"id":83272,"lat":0,"lng":0,"name":"景点地标","parentId":0,"regionType":0},{"id":83272,"lat":0,"lng":0,"name":"全部景点地标","parentId":83272,"regionType":0},{"id":83278,"lat":0,"lng":0,"name":"蜜蜂农场","parentId":83272,"regionType":0},{"id":83280,"lat":0,"lng":0,"name":"ICM商场","parentId":83272,"regionType":0},{"id":83279,"lat":0,"lng":0,"name":"眼镜猴保护中心","parentId":83272,"regionType":0}]