[{"id":-10000,"lat":0,"lng":0,"name":"热门商区","parentId":0,"regionType":0},{"id":0,"lat":0,"lng":0,"name":"全部商区","parentId":-10000,"regionType":0},{"id":73804,"lat":0,"lng":0,"name":"北环街","parentId":-10000,"regionType":0},{"id":73806,"lat":0,"lng":0,"name":"山阴华联商厦","parentId":-10000,"regionType":0},{"id":41822,"lat":0,"lng":0,"name":"岱岳镇","parentId":0,"regionType":0},{"id":41822,"lat":0,"lng":0,"name":"全部岱岳镇","parentId":41822,"regionType":0},{"id":3404,"lat":0,"lng":0,"name":"山阴县其他","parentId":0,"regionType":0},{"id":3404,"lat":0,"lng":0,"name":"全部山阴县其他","parentId":3404,"regionType":0},{"id":73804,"lat":0,"lng":0,"name":"北环街","parentId":3404,"regionType":0},{"id":73806,"lat":0,"lng":0,"name":"山阴华联商厦","parentId":3404,"regionType":0},{"id":41831,"lat":0,"lng":0,"name":"马营庄乡","parentId":0,"regionType":0},{"id":41831,"lat":0,"lng":0,"name":"全部马营庄乡","parentId":41831,"regionType":0},{"id":41820,"lat":0,"lng":0,"name":"北周庄镇","parentId":0,"regionType":0},{"id":41820,"lat":0,"lng":0,"name":"全部北周庄镇","parentId":41820,"regionType":0},{"id":41825,"lat":0,"lng":0,"name":"下喇叭乡","parentId":0,"regionType":0},{"id":41825,"lat":0,"lng":0,"name":"全部下喇叭乡","parentId":41825,"regionType":0},{"id":41828,"lat":0,"lng":0,"name":"薛圐圙乡","parentId":0,"regionType":0},{"id":41828,"lat":0,"lng":0,"name":"全部薛圐圙乡","parentId":41828,"regionType":0},{"id":41819,"lat":0,"lng":0,"name":"玉井镇","parentId":0,"regionType":0},{"id":41819,"lat":0,"lng":0,"name":"全部玉井镇","parentId":41819,"regionType":0},{"id":41821,"lat":0,"lng":0,"name":"古城镇","parentId":0,"regionType":0},{"id":41821,"lat":0,"lng":0,"name":"全部古城镇","parentId":41821,"regionType":0},{"id":41826,"lat":0,"lng":0,"name":"合盛堡乡","parentId":0,"regionType":0},{"id":41826,"lat":0,"lng":0,"name":"全部合盛堡乡","parentId":41826,"regionType":0},{"id":41829,"lat":0,"lng":0,"name":"后所乡","parentId":0,"regionType":0},{"id":41829,"lat":0,"lng":0,"name":"全部后所乡","parentId":41829,"regionType":0},{"id":41830,"lat":0,"lng":0,"name":"张家庄乡","parentId":0,"regionType":0},{"id":41830,"lat":0,"lng":0,"name":"全部张家庄乡","parentId":41830,"regionType":0},{"id":41824,"lat":0,"lng":0,"name":"马营乡","parentId":0,"regionType":0},{"id":41824,"lat":0,"lng":0,"name":"全部马营乡","parentId":41824,"regionType":0},{"id":41827,"lat":0,"lng":0,"name":"安荣乡","parentId":0,"regionType":0},{"id":41827,"lat":0,"lng":0,"name":"全部安荣乡","parentId":41827,"regionType":0},{"id":41823,"lat":0,"lng":0,"name":"吴马营乡","parentId":0,"regionType":0},{"id":41823,"lat":0,"lng":0,"name":"全部吴马营乡","parentId":41823,"regionType":0}]